MANIFEST.in
README.rst
setup.py
src/sentry_turbosms/__init__.py
src/sentry_turbosms/models.py
src/sentry_turbosms/plugin.py
src/sentry_turbosms.egg-info/PKG-INFO
src/sentry_turbosms.egg-info/SOURCES.txt
src/sentry_turbosms.egg-info/dependency_links.txt
src/sentry_turbosms.egg-info/entry_points.txt
src/sentry_turbosms.egg-info/not-zip-safe
src/sentry_turbosms.egg-info/requires.txt
src/sentry_turbosms.egg-info/top_level.txt