Metadata-Version: 1.1
Name: sentry-turbosms
Version: 0.0.1
Summary: A Sentry extension which integrates TurboSMS.
Home-page: https://github.com/gonsiorovsky/sentry-turbosms
Author: Denis Gonsiorovsky
Author-email: dns.gnsr@gmail.com
License: BSD
Platform: UNKNOWN
Classifier: Framework :: Django
Classifier: Intended Audience :: Developers
Classifier: Intended Audience :: System Administrators
Classifier: Operating System :: OS Independent
Classifier: Topic :: Software Development
